hurmodel/__init__.py
hurmodel/hurmodel.py
hurmodel-1.1.7.dist-info/LICENSE.txt
hurmodel-1.1.7.dist-info/METADATA
hurmodel-1.1.7.dist-info/WHEEL
hurmodel-1.1.7.dist-info/top_level.txt
hurmodel-1.1.7.dist-info/RECORD
