Metadata-Version: 2.2
Name: hurmodel
Version: 1.1.7
Home-page: https://github.com/sapiens-technology/hurmodel
Author: SAPIENS TECHNOLOGY
License: Proprietary Software
License-File: LICENSE.txt
Requires-Dist: torch
Requires-Dist: tiktoken
Requires-Dist: numpy
Requires-Dist: psutil
Requires-Dist: tqdm
Dynamic: author
Dynamic: home-page
Dynamic: license
Dynamic: requires-dist
